Metadata-Version: 2.4
Name: llama-index-vector-stores-alibabacloud-opensearch
Version: 0.4.0
Summary: llama-index vector_stores Alibaba Cloud OpenSearch integration
Author-email: goctave <gshuiwang@gmail.com>
License-Expression: MIT
License-File: LICENSE
Requires-Python: <4.0,>=3.9
Requires-Dist: alibabacloud-ha3engine-vector<2,>=1.1.8
Requires-Dist: llama-index-core<0.14,>=0.13.0
